aegis_sdk/__init__.py
aegis_sdk/audit.py
aegis_sdk/cli.py
aegis_sdk/license.py
aegis_sdk/metrics.py
aegis_sdk/types.py
aegis_sdk/batch/__init__.py
aegis_sdk/batch/csv_processor.py
aegis_sdk/batch/processor.py
aegis_sdk/core/__init__.py
aegis_sdk/core/detector.py
aegis_sdk/core/masker.py
aegis_sdk/core/policy.py
aegis_sdk/llm/__init__.py
aegis_sdk/llm/anthropic_wrapper.py
aegis_sdk/llm/gateway.py
aegis_sdk/llm/langchain_wrapper.py
aegis_sdk/llm/openai_wrapper.py
aegis_sdk-0.2.2.dist-info/METADATA
aegis_sdk-0.2.2.dist-info/WHEEL
aegis_sdk-0.2.2.dist-info/entry_points.txt
aegis_sdk-0.2.2.dist-info/RECORD
