Metadata-Version: 2.4
Name: aegis-sdk
Version: 0.2.2
Summary: On-premise PII detection and masking for AI applications
Project-URL: Homepage, https://www.aegispreflight.com/
Project-URL: Documentation, https://docs.aegispreflight.com
Author-email: Aegis Preflight Team <support@aegispreflight.com>
License: Proprietary
Keywords: ai,gdpr,hipaa,llm,masking,pii,privacy
Classifier: Development Status :: 4 - Beta
Classifier: Intended Audience :: Developers
Classifier: License :: Other/Proprietary License
Classifier: Operating System :: OS Independent
Classifier: Programming Language :: Python :: 3
Classifier: Programming Language :: Python :: 3.9
Classifier: Programming Language :: Python :: 3.10
Classifier: Programming Language :: Python :: 3.11
Classifier: Programming Language :: Python :: 3.12
Classifier: Programming Language :: Python :: 3.13
Classifier: Topic :: Security
Classifier: Topic :: Software Development :: Libraries :: Python Modules
Classifier: Typing :: Typed
Requires-Python: >=3.9
Requires-Dist: aegis-preflight-core>=0.1.0
Provides-Extra: all
Requires-Dist: anthropic>=0.18; extra == 'all'
Requires-Dist: langchain>=0.1; extra == 'all'
Requires-Dist: openai>=1.0; extra == 'all'
Requires-Dist: pyjwt[crypto]>=2.8.0; extra == 'all'
Provides-Extra: anthropic
Requires-Dist: anthropic>=0.18; extra == 'anthropic'
Provides-Extra: dev
Requires-Dist: black>=23.0; extra == 'dev'
Requires-Dist: mypy>=1.0; extra == 'dev'
Requires-Dist: pytest-cov>=4.0; extra == 'dev'
Requires-Dist: pytest>=7.0; extra == 'dev'
Requires-Dist: ruff>=0.1; extra == 'dev'
Provides-Extra: jwt
Requires-Dist: pyjwt[crypto]>=2.8.0; extra == 'jwt'
Provides-Extra: langchain
Requires-Dist: langchain>=0.1; extra == 'langchain'
Provides-Extra: openai
Requires-Dist: openai>=1.0; extra == 'openai'
